LICENSE.txt
MANIFEST.in
README.rst
setup.py
examples/time_chem/setup.py
examples/time_chem/time_chem/__init__.py
mrpump/__init__.py
mrpump/auth.py
mrpump/chem.py
mrpump/drive.py
mrpump/forehead.py
mrpump/ping_chem.py
mrpump.egg-info/PKG-INFO
mrpump.egg-info/SOURCES.txt
mrpump.egg-info/dependency_links.txt
mrpump.egg-info/entry_points.txt
mrpump.egg-info/requires.txt
mrpump.egg-info/top_level.txt
mrpump.egg-info/zip-safe
scripts/emet