Metadata-Version: 1.1
Name: mrpump
Version: 0.2
Summary: A twitter bot extensible by means of eggs
Home-page: http://github.com/jaredjennings/mrpump
Author: Jared Jennings
Author-email: jjennings@fastmail.fm
License: GPLv3 or later
Keywords: twitter bot
Platform: UNKNOWN
Classifier: License :: OSI Approved :: GNU General Public License v3 or later (GPLv3+)
Classifier: Environment :: Console
Classifier: Topic :: Communications
